{"v":"5.1.20","fr":30,"ip":0,"op":74,"w":1000,"h":1000,"nm":"Comp 3","ddd":0,"assets":[{"id":"comp_0","layers":[{"ddd":0,"ind":1,"ty":0,"nm":"Pre-comp 3","refId":"comp_1","sr":1,"ks":{"o":{"a":0,"k":100,"ix":11},"r":{"a":0,"k":0,"ix":10},"p":{"a":0,"k":[441,611,0],"ix":2},"a":{"a":0,"k":[350,350,0],"ix":1},"s":{"a":0,"k":[100,100,100],"ix":6}},"ao":0,"w":700,"h":700,"ip":22,"op":735,"st":22,"bm":0},{"ddd":0,"ind":2,"ty":0,"nm":"Pre-comp 2","refId":"comp_2","sr":1,"ks":{"o":{"a":0,"k":100,"ix":11},"r":{"a":0,"k":0,"ix":10},"p":{"a":0,"k":[637,607,0],"ix":2},"a":{"a":0,"k":[350,350,0],"ix":1},"s":{"a":0,"k":[100,100,100],"ix":6}},"ao":0,"w":700,"h":700,"ip":30,"op":743,"st":30,"bm":0},{"ddd":0,"ind":3,"ty":0,"nm":"Pre-comp 1","refId":"comp_3","sr":1,"ks":{"o":{"a":0,"k":100,"ix":11},"r":{"a":0,"k":0,"ix":10},"p":{"a":0,"k":[646,154.719,0],"ix":2},"a":{"a":0,"k":[350,350,0],"ix":1},"s":{"a":0,"k":[100,100,100],"ix":6}},"ao":0,"w":700,"h":700,"ip":11,"op":724,"st":11,"bm":0},{"ddd":0,"ind":4,"ty":0,"nm":"Pre-comp 2","refId":"comp_2","sr":1,"ks":{"o":{"a":0,"k":100,"ix":11},"r":{"a":0,"k":0,"ix":10},"p":{"a":0,"k":[641,147,0],"ix":2},"a":{"a":0,"k":[350,350,0],"ix":1},"s":{"a":0,"k":[100,100,100],"ix":6}},"ao":0,"w":700,"h":700,"ip":10,"op":723,"st":10,"bm":0},{"ddd":0,"ind":5,"ty":0,"nm":"ball","refId":"comp_4","sr":1,"ks":{"o":{"a":0,"k":100,"ix":11},"r":{"a":0,"k":0,"ix":10},"p":{"a":1,"k":[{"i":{"x":0,"y":1},"o":{"x":0.333,"y":0},"n":"0_1_0p333_0","t":0,"s":[636,618,0],"e":[534,130,0],"to":[77,-381.666656494141,0],"ti":[26.4810428619385,2.57427310943604,0]},{"i":{"x":0,"y":1},"o":{"x":0.333,"y":0},"n":"0_1_0p333_0","t":12,"s":[534,130,0],"e":[390,259,0],"to":[-26.4923458099365,-2.57537198066711,0],"ti":[23.7114067077637,-15.8076038360596,0]},{"i":{"x":0,"y":1},"o":{"x":0.333,"y":0},"n":"0_1_0p333_0","t":21,"s":[390,259,0],"e":[382,152,0],"to":[-13,8.66666698455811,0],"ti":[0.33333334326744,103.833335876465,0]},{"i":{"x":0,"y":1},"o":{"x":0.333,"y":0},"n":"0_1_0p333_0","t":30,"s":[382,152,0],"e":[380.585,82.809,0],"to":[-0.01140431407839,-3.55244374275208,0],"ti":[0.03035433217883,-34.3619232177734,0]},{"i":{"x":0,"y":1},"o":{"x":0.333,"y":0},"n":"0_1_0p333_0","t":31,"s":[380.585,82.809,0],"e":[382,719,0],"to":[-0.12244949489832,138.616134643555,0],"ti":[0.80135095119476,-5.07522296905518,0]},{"i":{"x":0,"y":1},"o":{"x":0.333,"y":0},"n":"0_1_0p333_0","t":42,"s":[382,719,0],"e":[382,625.5,0],"to":[-1,6.33333349227905,0],"ti":[0,0.16666667163372,0]},{"t":54}],"ix":2},"a":{"a":0,"k":[32,35,0],"ix":1},"s":{"a":1,"k":[{"i":{"x":[0,0,0.667],"y":[1,1,1]},"o":{"x":[0.333,0.333,0.333],"y":[0,0,0]},"n":["0_1_0p333_0","0_1_0p333_0","0p667_1_0p333_0"],"t":22,"s":[100,100,100],"e":[100,74.286,100]},{"i":{"x":[0.667,0.667,0.667],"y":[1,1,1]},"o":{"x":[0.333,0.333,0.333],"y":[0,0,0]},"n":["0p667_1_0p333_0","0p667_1_0p333_0","0p667_1_0p333_0"],"t":23,"s":[100,74.286,100],"e":[100,74.286,100]},{"i":{"x":[0,0,0.667],"y":[1,1,1]},"o":{"x":[0.333,0.333,0.333],"y":[0,0,0]},"n":["0_1_0p333_0","0_1_0p333_0","0p667_1_0p333_0"],"t":28,"s":[100,74.286,100],"e":[100,100,100]},{"i":{"x":[0.667,0.667,0.667],"y":[1,1,1]},"o":{"x":[0.333,0.333,0.333],"y":[0,0,0]},"n":["0p667_1_0p333_0","0p667_1_0p333_0","0p667_1_0p333_0"],"t":29,"s":[100,100,100],"e":[100,100,100]},{"i":{"x":[0,0,0.667],"y":[1,1,1]},"o":{"x":[0.333,0.333,0.333],"y":[0,0,0]},"n":["0_1_0p333_0","0_1_0p333_0","0p667_1_0p333_0"],"t":38,"s":[100,100,100],"e":[100,80,100]},{"i":{"x":[0.667,0.667,0.667],"y":[1,1,1]},"o":{"x":[0.333,0.333,0.333],"y":[0,0,0]},"n":["0p667_1_0p333_0","0p667_1_0p333_0","0p667_1_0p333_0"],"t":41,"s":[100,80,100],"e":[100,80,100]},{"i":{"x":[0,0,0.667],"y":[1,1,1]},"o":{"x":[0.333,0.333,0.333],"y":[0,0,0]},"n":["0_1_0p333_0","0_1_0p333_0","0p667_1_0p333_0"],"t":45,"s":[100,80,100],"e":[100,100,100]},{"t":48}],"ix":6}},"ao":0,"w":64,"h":70,"ip":0,"op":713,"st":0,"bm":0},{"ddd":0,"ind":6,"ty":0,"nm":"ball","parent":9,"refId":"comp_4","sr":1,"ks":{"o":{"a":0,"k":100,"ix":11},"r":{"a":0,"k":0,"ix":10},"p":{"a":1,"k":[{"i":{"x":0.833,"y":0.833},"o":{"x":0.167,"y":0.167},"n":"0p833_0p833_0p167_0p167","t":0,"s":[-108,-115,0],"e":[135.556,122.762,0],"to":[40.5927467346191,39.6270713806152,0],"ti":[-40.5927467346191,-39.6270713806152,0]},{"t":3}],"ix":2},"a":{"a":0,"k":[32,35,0],"ix":1},"s":{"a":0,"k":[100,100,100],"ix":6}},"ao":0,"w":64,"h":70,"ip":0,"op":713,"st":0,"bm":0},{"ddd":0,"ind":7,"ty":0,"nm":"tile 2","parent":11,"refId":"comp_5","sr":1,"ks":{"o":{"a":0,"k":100,"ix":11},"r":{"a":0,"k":0,"ix":10},"p":{"a":0,"k":[-107,123,0],"ix":2},"a":{"a":0,"k":[126.5,127,0],"ix":1},"s":{"a":0,"k":[100,100,100],"ix":6}},"ao":0,"w":253,"h":254,"ip":0,"op":713,"st":0,"bm":0},{"ddd":0,"ind":8,"ty":0,"nm":"tile 2","parent":11,"refId":"comp_5","sr":1,"ks":{"o":{"a":0,"k":100,"ix":11},"r":{"a":0,"k":0,"ix":10},"p":{"a":0,"k":[122,-105,0],"ix":2},"a":{"a":0,"k":[126.5,127,0],"ix":1},"s":{"a":0,"k":[100,100,100],"ix":6}},"ao":0,"w":253,"h":254,"ip":0,"op":713,"st":0,"bm":0},{"ddd":0,"ind":9,"ty":0,"nm":"tile1","parent":11,"refId":"comp_6","sr":1,"ks":{"o":{"a":0,"k":100,"ix":11},"r":{"a":0,"k":0,"ix":10},"p":{"a":0,"k":[126,122,0],"ix":2},"a":{"a":0,"k":[124.5,128.5,0],"ix":1},"s":{"a":0,"k":[100,100,100],"ix":6}},"ao":0,"w":249,"h":257,"ip":0,"op":713,"st":0,"bm":0},{"ddd":0,"ind":10,"ty":0,"nm":"tile1","parent":11,"refId":"comp_6","sr":1,"ks":{"o":{"a":0,"k":100,"ix":11},"r":{"a":0,"k":0,"ix":10},"p":{"a":0,"k":[-107,-109,0],"ix":2},"a":{"a":0,"k":[124.5,128.5,0],"ix":1},"s":{"a":0,"k":[100,100,100],"ix":6}},"ao":0,"w":249,"h":257,"ip":0,"op":713,"st":0,"bm":0},{"ddd":0,"ind":11,"ty":4,"nm":"Shape Layer 1","sr":1,"ks":{"o":{"a":0,"k":100,"ix":11},"r":{"a":1,"k":[{"i":{"x":[0],"y":[1.001]},"o":{"x":[0.333],"y":[-0.153]},"n":["0_1p001_0p333_-0p153"],"t":0,"s":[0],"e":[-90]},{"t":23}],"ix":10},"p":{"a":1,"k":[{"i":{"x":0,"y":1},"o":{"x":0.333,"y":0},"n":"0_1_0p333_0","t":0,"s":[500,500,0],"e":[502,518,0],"to":[0.33333334326744,3,0],"ti":[-0.33333334326744,-3,0]},{"t":23}],"ix":2},"a":{"a":0,"k":[0,0,0],"ix":1},"s":{"a":0,"k":[100,100,100],"ix":6}},"ao":0,"shapes":[{"ty":"gr","it":[{"ty":"rc","d":1,"s":{"a":0,"k":[245,221],"ix":2},"p":{"a":0,"k":[0,0],"ix":3},"r":{"a":0,"k":0,"ix":4},"nm":"Rectangle Path 1","mn":"ADBE Vector Shape - Rect","hd":false},{"ty":"st","c":{"a":0,"k":[0.996078012504,0.02734300015,0.02734300015,1],"ix":3},"o":{"a":0,"k":100,"ix":4},"w":{"a":0,"k":1,"ix":5},"lc":1,"lj":1,"ml":4,"nm":"Stroke 1","mn":"ADBE Vector Graphic - Stroke","hd":false},{"ty":"tr","p":{"a":0,"k":[18.5,12.5],"ix":2},"a":{"a":0,"k":[0,0],"ix":1},"s":{"a":0,"k":[100,100],"ix":3},"r":{"a":0,"k":0,"ix":6},"o":{"a":0,"k":100,"ix":7},"sk":{"a":0,"k":0,"ix":4},"sa":{"a":0,"k":0,"ix":5},"nm":"Transform"}],"nm":"Rectangle 1","np":3,"cix":2,"ix":1,"mn":"ADBE Vector Group","hd":false}],"ip":0,"op":713,"st":0,"bm":0}]},{"id":"comp_1","layers":[{"ddd":0,"ind":1,"ty":4,"nm":"Shape Layer 3","sr":1,"ks":{"o":{"a":0,"k":100,"ix":11},"r":{"a":0,"k":0,"ix":10},"p":{"a":1,"k":[{"i":{"x":0,"y":1},"o":{"x":1,"y":0},"n":"0_1_1_0","t":28,"s":[309.375,443.75,0],"e":[333.25,430.25,0],"to":[3.97916674613953,-2.25,0],"ti":[-17.0680637359619,-12.1429300308228,0]},{"i":{"x":0,"y":1},"o":{"x":1,"y":0},"n":"0_1_1_0","t":32,"s":[333.25,430.25,0],"e":[347.125,467.22,0],"to":[13.3565654754639,9.50241565704346,0],"ti":[-0.0625,-0.16666667163372,0]},{"i":{"x":0.335,"y":0},"o":{"x":0.665,"y":1},"n":"0p335_0_0p665_1","t":35,"s":[347.125,467.22,0],"e":[356.375,450.095,0],"to":[0.0625,0.16666667163372,0],"ti":[-0.0625,0,0]},{"t":39}],"ix":2},"a":{"a":0,"k":[-31,94,0],"ix":1},"s":{"a":1,"k":[{"i":{"x":[0.667,0.667,0.667],"y":[1,1,1]},"o":{"x":[1,1,0.333],"y":[0,0,0]},"n":["0p667_1_1_0","0p667_1_1_0","0p667_1_0p333_0"],"t":28,"s":[100,100,100],"e":[112,112,100]},{"i":{"x":[0,0,0.667],"y":[58.227,58.227,1]},"o":{"x":[0.997,0.997,0.333],"y":[0,0,0]},"n":["0_58p227_0p997_0","0_58p227_0p997_0","0p667_1_0p333_0"],"t":32,"s":[112,112,100],"e":[112,112,100]},{"i":{"x":[0,0,0.667],"y":[1.196,1.196,1]},"o":{"x":[1,1,0.333],"y":[0.241,0.241,0]},"n":["0_1p196_1_0p241","0_1p196_1_0p241","0p667_1_0p333_0"],"t":38,"s":[112,112,100],"e":[0,0,100]},{"t":41}],"ix":6}},"ao":0,"shapes":[{"ty":"gr","it":[{"ind":0,"ty":"sh","ix":1,"ks":{"a":0,"k":{"i":[[0,0],[0,0],[0,0],[0,0]],"o":[[0,0],[0,0],[0,0],[0,0]],"v":[[-32.5,90.125],[-35.375,94.375],[-31.5,97.375],[-28.375,93.625]],"c":true},"ix":2},"nm":"Path 1","mn":"ADBE Vector Shape - Group","hd":false},{"ty":"fl","c":{"a":0,"k":[1,0,0,1],"ix":4},"o":{"a":0,"k":100,"ix":5},"r":1,"nm":"Fill 1","mn":"ADBE Vector Graphic - Fill","hd":false},{"ty":"tr","p":{"a":0,"k":[0,0],"ix":2},"a":{"a":0,"k":[0,0],"ix":1},"s":{"a":0,"k":[100,100],"ix":3},"r":{"a":0,"k":0,"ix":6},"o":{"a":0,"k":100,"ix":7},"sk":{"a":0,"k":0,"ix":4},"sa":{"a":0,"k":0,"ix":5},"nm":"Transform"}],"nm":"Shape 1","np":3,"cix":2,"ix":1,"mn":"ADBE Vector Group","hd":false}],"ip":26,"op":44,"st":0,"bm":0},{"ddd":0,"ind":2,"ty":4,"nm":"Shape Layer 2","sr":1,"ks":{"o":{"a":0,"k":100,"ix":11},"r":{"a":0,"k":0,"ix":10},"p":{"a":1,"k":[{"i":{"x":0.667,"y":1},"o":{"x":0.333,"y":0},"n":"0p667_1_0p333_0","t":28,"s":[282.125,435.25,0],"e":[267.25,418.875,0],"to":[-2.47916674613953,-2.72916674613953,0],"ti":[14.1533451080322,-4.08456563949585,0]},{"i":{"x":0.667,"y":1},"o":{"x":0.333,"y":0},"n":"0p667_1_0p333_0","t":32,"s":[267.25,418.875,0],"e":[247,450.75,0],"to":[-13.6549119949341,3.94072103500366,0],"ti":[0,0,0]},{"i":{"x":0.667,"y":1},"o":{"x":0.333,"y":0},"n":"0p667_1_0p333_0","t":35,"s":[247,450.75,0],"e":[243.125,468.62,0],"to":[0,0,0],"ti":[0,0,0]},{"t":39}],"ix":2},"a":{"a":0,"k":[-47.75,90.75,0],"ix":1},"s":{"a":1,"k":[{"i":{"x":[0.667,0.667,0.667],"y":[1,1,1]},"o":{"x":[0.333,0.333,0.333],"y":[0,0,0]},"n":["0p667_1_0p333_0","0p667_1_0p333_0","0p667_1_0p333_0"],"t":28,"s":[100,100,100],"e":[112,112,100]},{"i":{"x":[0.667,0.667,0.667],"y":[1,1,1]},"o":{"x":[0.333,0.333,0.333],"y":[0,0,0]},"n":["0p667_1_0p333_0","0p667_1_0p333_0","0p667_1_0p333_0"],"t":32,"s":[112,112,100],"e":[112,112,100]},{"i":{"x":[0.667,0.667,0.667],"y":[1,1,1]},"o":{"x":[0.333,0.333,0.333],"y":[0,0,0]},"n":["0p667_1_0p333_0","0p667_1_0p333_0","0p667_1_0p333_0"],"t":38,"s":[112,112,100],"e":[0,0,100]},{"t":41}],"ix":6}},"ao":0,"shapes":[{"ty":"gr","it":[{"ty":"rc","d":1,"s":{"a":0,"k":[5.875,4.875],"ix":2},"p":{"a":0,"k":[0,0],"ix":3},"r":{"a":0,"k":0,"ix":4},"nm":"Rectangle Path 1","mn":"ADBE Vector Shape - Rect","hd":false},{"ty":"fl","c":{"a":0,"k":[0.833343146829,0.945098039216,0.081537867527,1],"ix":4},"o":{"a":0,"k":100,"ix":5},"r":1,"nm":"Fill 1","mn":"ADBE Vector Graphic - Fill","hd":false},{"ty":"tr","p":{"a":0,"k":[-47.813,90.438],"ix":2},"a":{"a":0,"k":[0,0],"ix":1},"s":{"a":0,"k":[100,100],"ix":3},"r":{"a":0,"k":0,"ix":6},"o":{"a":0,"k":100,"ix":7},"sk":{"a":0,"k":0,"ix":4},"sa":{"a":0,"k":0,"ix":5},"nm":"Transform"}],"nm":"Rectangle 1","np":3,"cix":2,"ix":1,"mn":"ADBE Vector Group","hd":false}],"ip":26,"op":44,"st":0,"bm":0},{"ddd":0,"ind":3,"ty":4,"nm":"Shape Layer 1","sr":1,"ks":{"o":{"a":0,"k":100,"ix":11},"r":{"a":0,"k":0,"ix":10},"p":{"a":1,"k":[{"i":{"x":0.667,"y":1},"o":{"x":0.333,"y":0},"n":"0p667_1_0p333_0","t":28,"s":[274.875,451.5,0],"e":[254.5,437.5,0],"to":[-3.39583325386047,-2.33333325386047,0],"ti":[14.240029335022,-4.44992971420288,0]},{"i":{"x":0.667,"y":1},"o":{"x":0.333,"y":0},"n":"0p667_1_0p333_0","t":32,"s":[254.5,437.5,0],"e":[239.25,468.9,0],"to":[-12.8637771606445,4.01985883712769,0],"ti":[0.71875,-0.19791667163372,0]},{"i":{"x":0.667,"y":1},"o":{"x":0.333,"y":0},"n":"0p667_1_0p333_0","t":35,"s":[239.25,468.9,0],"e":[228.125,453.4,0],"to":[-0.28968080878258,0.07976718246937,0],"ti":[0,0,0]},{"t":39}],"ix":2},"a":{"a":0,"k":[-72.75,94.75,0],"ix":1},"s":{"a":1,"k":[{"i":{"x":[0.667,0.667,0.667],"y":[1,1,1]},"o":{"x":[0.333,0.333,0.333],"y":[0,0,0]},"n":["0p667_1_0p333_0","0p667_1_0p333_0","0p667_1_0p333_0"],"t":28,"s":[100,100,100],"e":[112,112,100]},{"i":{"x":[0.667,0.667,0.667],"y":[1,1,1]},"o":{"x":[0.333,0.333,0.333],"y":[0,0,0]},"n":["0p667_1_0p333_0","0p667_1_0p333_0","0p667_1_0p333_0"],"t":32,"s":[112,112,100],"e":[112,112,100]},{"i":{"x":[0.667,0.667,0.667],"y":[1,1,1]},"o":{"x":[0.333,0.333,0.333],"y":[0,0,0]},"n":["0p667_1_0p333_0","0p667_1_0p333_0","0p667_1_0p333_0"],"t":38,"s":[112,112,100],"e":[0,0,100]},{"t":41}],"ix":6}},"ao":0,"shapes":[{"ty":"gr","it":[{"d":1,"ty":"el","s":{"a":0,"k":[4.625,4.5],"ix":2},"p":{"a":0,"k":[0,0],"ix":3},"nm":"Ellipse Path 1","mn":"ADBE Vector Shape - Ellipse","hd":false},{"ty":"fl","c":{"a":0,"k":[0.960784313725,0.651826207778,0.651826207778,1],"ix":4},"o":{"a":0,"k":100,"ix":5},"r":1,"nm":"Fill 1","mn":"ADBE Vector Graphic - Fill","hd":false},{"ty":"tr","p":{"a":0,"k":[-72.688,94.375],"ix":2},"a":{"a":0,"k":[0,0],"ix":1},"s":{"a":0,"k":[100,100],"ix":3},"r":{"a":0,"k":0,"ix":6},"o":{"a":0,"k":100,"ix":7},"sk":{"a":0,"k":0,"ix":4},"sa":{"a":0,"k":0,"ix":5},"nm":"Transform"}],"nm":"Ellipse 1","np":3,"cix":2,"ix":1,"mn":"ADBE Vector Group","hd":false}],"ip":26,"op":44,"st":0,"bm":0}]},{"id":"comp_2","layers":[{"ddd":0,"ind":1,"ty":4,"nm":"spark2","sr":1,"ks":{"o":{"a":0,"k":100,"ix":11},"r":{"a":0,"k":0,"ix":10},"p":{"a":0,"k":[79,475.5,0],"ix":2},"a":{"a":0,"k":[-234,124.279,0],"ix":1},"s":{"a":0,"k":[-100,88.511,100],"ix":6}},"ao":0,"shapes":[{"ty":"gr","it":[{"ind":0,"ty":"sh","ix":1,"ks":{"a":0,"k":{"i":[[0,-2.5],[-13,0]],"o":[[0,2.5],[13,0]],"v":[[-242,127.5],[-226,117.5]],"c":false},"ix":2},"nm":"Path 1","mn":"ADBE Vector Shape - Group","hd":false},{"ty":"st","c":{"a":0,"k":[0.541176350911,0,1,1],"ix":3},"o":{"a":0,"k":100,"ix":4},"w":{"a":0,"k":2,"ix":5},"lc":1,"lj":1,"ml":4,"nm":"Stroke 1","mn":"ADBE Vector Graphic - Stroke","hd":false},{"ty":"tr","p":{"a":0,"k":[0,0],"ix":2},"a":{"a":0,"k":[0,0],"ix":1},"s":{"a":0,"k":[100,100],"ix":3},"r":{"a":0,"k":0,"ix":6},"o":{"a":0,"k":100,"ix":7},"sk":{"a":0,"k":0,"ix":4},"sa":{"a":0,"k":0,"ix":5},"nm":"Transform"}],"nm":"Shape 1","np":3,"cix":2,"ix":1,"mn":"ADBE Vector Group","hd":false},{"ty":"tm","s":{"a":0,"k":0,"ix":1},"e":{"a":1,"k":[{"i":{"x":[0.833],"y":[0.833]},"o":{"x":[0.167],"y":[0.167]},"n":["0p833_0p833_0p167_0p167"],"t":12,"s":[0],"e":[100]},{"i":{"x":[0.833],"y":[0.833]},"o":{"x":[0.167],"y":[0.167]},"n":["0p833_0p833_0p167_0p167"],"t":14,"s":[100],"e":[100]},{"i":{"x":[0.833],"y":[0.833]},"o":{"x":[0.167],"y":[0.167]},"n":["0p833_0p833_0p167_0p167"],"t":20,"s":[100],"e":[0]},{"t":22}],"ix":2},"o":{"a":0,"k":0,"ix":3},"m":1,"ix":2,"nm":"Trim Paths 1","mn":"ADBE Vector Filter - Trim","hd":false}],"ip":0,"op":31,"st":0,"bm":0},{"ddd":0,"ind":2,"ty":4,"nm":"spark1","sr":1,"ks":{"o":{"a":0,"k":100,"ix":11},"r":{"a":0,"k":0,"ix":10},"p":{"a":0,"k":[114,472.5,0],"ix":2},"a":{"a":0,"k":[-236,122.5,0],"ix":1},"s":{"a":0,"k":[100,100,100],"ix":6}},"ao":0,"shapes":[{"ty":"gr","it":[{"ind":0,"ty":"sh","ix":1,"ks":{"a":0,"k":{"i":[[0,-2.5],[-13,0]],"o":[[0,2.5],[13,0]],"v":[[-242,127.5],[-226,117.5]],"c":false},"ix":2},"nm":"Path 1","mn":"ADBE Vector Shape - Group","hd":false},{"ty":"st","c":{"a":0,"k":[0.541176350911,0,1,1],"ix":3},"o":{"a":0,"k":100,"ix":4},"w":{"a":0,"k":2,"ix":5},"lc":1,"lj":1,"ml":4,"nm":"Stroke 1","mn":"ADBE Vector Graphic - Stroke","hd":false},{"ty":"tr","p":{"a":0,"k":[0,0],"ix":2},"a":{"a":0,"k":[0,0],"ix":1},"s":{"a":0,"k":[100,100],"ix":3},"r":{"a":0,"k":0,"ix":6},"o":{"a":0,"k":100,"ix":7},"sk":{"a":0,"k":0,"ix":4},"sa":{"a":0,"k":0,"ix":5},"nm":"Transform"}],"nm":"Shape 1","np":3,"cix":2,"ix":1,"mn":"ADBE Vector Group","hd":false},{"ty":"tm","s":{"a":0,"k":0,"ix":1},"e":{"a":1,"k":[{"i":{"x":[0.833],"y":[0.833]},"o":{"x":[0.167],"y":[0.167]},"n":["0p833_0p833_0p167_0p167"],"t":12,"s":[0],"e":[100]},{"i":{"x":[0.833],"y":[0.833]},"o":{"x":[0.167],"y":[0.167]},"n":["0p833_0p833_0p167_0p167"],"t":14,"s":[100],"e":[100]},{"i":{"x":[0.833],"y":[0.833]},"o":{"x":[0.167],"y":[0.167]},"n":["0p833_0p833_0p167_0p167"],"t":20,"s":[100],"e":[0]},{"t":22}],"ix":2},"o":{"a":0,"k":0,"ix":3},"m":1,"ix":2,"nm":"Trim Paths 1","mn":"ADBE Vector Filter - Trim","hd":false}],"ip":0,"op":31,"st":0,"bm":0}]},{"id":"comp_3","layers":[{"ddd":0,"ind":1,"ty":4,"nm":"Shape Layer 6","sr":1,"ks":{"o":{"a":0,"k":100,"ix":11},"r":{"a":1,"k":[{"i":{"x":[0.833],"y":[0.833]},"o":{"x":[0.167],"y":[0.167]},"n":["0p833_0p833_0p167_0p167"],"t":15,"s":[0],"e":[-104]},{"i":{"x":[0.833],"y":[0.833]},"o":{"x":[0.167],"y":[0.167]},"n":["0p833_0p833_0p167_0p167"],"t":26,"s":[-104],"e":[-24]},{"t":29}],"ix":10},"p":{"a":1,"k":[{"i":{"x":0.833,"y":0.833},"o":{"x":0.167,"y":0.167},"n":"0p833_0p833_0p167_0p167","t":15,"s":[88,432.5,0],"e":[87.75,411.25,0],"to":[-1.54166662693024,-12.5416669845581,0],"ti":[6.50537633895874,-0.34541821479797,0]},{"i":{"x":0.833,"y":0.833},"o":{"x":0.167,"y":0.167},"n":"0p833_0p833_0p167_0p167","t":21,"s":[87.75,411.25,0],"e":[61.25,461,0],"to":[-32.9583320617676,1.75,0],"ti":[5.125,-10.8352966308594,0]},{"i":{"x":0.833,"y":0.833},"o":{"x":0.167,"y":0.167},"n":"0p833_0p833_0p167_0p167","t":26,"s":[61.25,461,0],"e":[57,476.262,0],"to":[-5.125,10.8352966308594,0],"ti":[0.70833331346512,-2.54362988471985,0]},{"t":29}],"ix":2},"a":{"a":0,"k":[-230.5,95.5,0],"ix":1},"s":{"a":1,"k":[{"i":{"x":[0.667,0.667,0.667],"y":[1,1,1]},"o":{"x":[0.333,0.333,0.333],"y":[0,0,0]},"n":["0p667_1_0p333_0","0p667_1_0p333_0","0p667_1_0p333_0"],"t":15,"s":[65,65,100],"e":[37,37,100]},{"i":{"x":[0.667,0.667,0.667],"y":[1,1,1]},"o":{"x":[0.333,0.333,0.333],"y":[0,0,0]},"n":["0p667_1_0p333_0","0p667_1_0p333_0","0p667_1_0p333_0"],"t":20,"s":[37,37,100],"e":[70,70,100]},{"i":{"x":[0.667,0.667,0.667],"y":[1,1,1]},"o":{"x":[0.333,0.333,0.333],"y":[0,0,0]},"n":["0p667_1_0p333_0","0p667_1_0p333_0","0p667_1_0p333_0"],"t":21,"s":[70,70,100],"e":[0,0,100]},{"t":29}],"ix":6}},"ao":0,"shapes":[{"ty":"gr","it":[{"d":1,"ty":"el","s":{"a":0,"k":[9.5,9.5],"ix":2},"p":{"a":0,"k":[0,0],"ix":3},"nm":"Ellipse Path 1","mn":"ADBE Vector Shape - Ellipse","hd":false},{"ty":"fl","c":{"a":0,"k":[0.364705882353,0.035755479102,0.035755479102,1],"ix":4},"o":{"a":0,"k":100,"ix":5},"r":1,"nm":"Fill 1","mn":"ADBE Vector Graphic - Fill","hd":false},{"ty":"tr","p":{"a":0,"k":[-231.25,95.25],"ix":2},"a":{"a":0,"k":[0,0],"ix":1},"s":{"a":0,"k":[100,100],"ix":3},"r":{"a":0,"k":0,"ix":6},"o":{"a":0,"k":100,"ix":7},"sk":{"a":0,"k":0,"ix":4},"sa":{"a":0,"k":0,"ix":5},"nm":"Transform"}],"nm":"Ellipse 1","np":3,"cix":2,"ix":1,"mn":"ADBE Vector Group","hd":false}],"ip":13,"op":31,"st":13,"bm":0},{"ddd":0,"ind":2,"ty":4,"nm":"Shape Layer 5","sr":1,"ks":{"o":{"a":0,"k":100,"ix":11},"r":{"a":1,"k":[{"i":{"x":[0.833],"y":[0.833]},"o":{"x":[0.167],"y":[0.167]},"n":["0p833_0p833_0p167_0p167"],"t":15,"s":[0],"e":[-104]},{"i":{"x":[0.833],"y":[0.833]},"o":{"x":[0.167],"y":[0.167]},"n":["0p833_0p833_0p167_0p167"],"t":26,"s":[-104],"e":[-24]},{"t":29}],"ix":10},"p":{"a":1,"k":[{"i":{"x":0.833,"y":0.833},"o":{"x":0.167,"y":0.167},"n":"0p833_0p833_0p167_0p167","t":15,"s":[120.5,451.75,0],"e":[143.75,446.5,0],"to":[11.875,-10.625,0],"ti":[-5.23719453811646,-4.99027538299561,0]},{"i":{"x":0.833,"y":0.833},"o":{"x":0.167,"y":0.167},"n":"0p833_0p833_0p167_0p167","t":21,"s":[143.75,446.5,0],"e":[155.75,477.075,0],"to":[13.875,13.220832824707,0],"ti":[-3.75,-2.26249957084656,0]},{"i":{"x":0.833,"y":0.833},"o":{"x":0.167,"y":0.167},"n":"0p833_0p833_0p167_0p167","t":26,"s":[155.75,477.075,0],"e":[166.25,460.075,0],"to":[3.75,2.26249957084656,0],"ti":[-8.71875,6.67708349227905,0]},{"t":29}],"ix":2},"a":{"a":0,"k":[-230.5,95.5,0],"ix":1},"s":{"a":1,"k":[{"i":{"x":[0.667,0.667,0.667],"y":[1,1,1]},"o":{"x":[0.333,0.333,0.333],"y":[0,0,0]},"n":["0p667_1_0p333_0","0p667_1_0p333_0","0p667_1_0p333_0"],"t":15,"s":[42,42,100],"e":[14,14,100]},{"i":{"x":[0.667,0.667,0.667],"y":[1,1,1]},"o":{"x":[0.333,0.333,0.333],"y":[0,0,0]},"n":["0p667_1_0p333_0","0p667_1_0p333_0","0p667_1_0p333_0"],"t":20,"s":[14,14,100],"e":[47,47,100]},{"i":{"x":[0.667,0.667,0.667],"y":[1,1,1]},"o":{"x":[0.333,0.333,0.333],"y":[0,0,0]},"n":["0p667_1_0p333_0","0p667_1_0p333_0","0p667_1_0p333_0"],"t":21,"s":[47,47,100],"e":[0,0,100]},{"t":29}],"ix":6}},"ao":0,"shapes":[{"ty":"gr","it":[{"d":1,"ty":"el","s":{"a":0,"k":[9.5,9.5],"ix":2},"p":{"a":0,"k":[0,0],"ix":3},"nm":"Ellipse Path 1","mn":"ADBE Vector Shape - Ellipse","hd":false},{"ty":"fl","c":{"a":0,"k":[0.94117641075,1,0,1],"ix":4},"o":{"a":0,"k":100,"ix":5},"r":1,"nm":"Fill 1","mn":"ADBE Vector Graphic - Fill","hd":false},{"ty":"tr","p":{"a":0,"k":[-231.25,95.25],"ix":2},"a":{"a":0,"k":[0,0],"ix":1},"s":{"a":0,"k":[100,100],"ix":3},"r":{"a":0,"k":0,"ix":6},"o":{"a":0,"k":100,"ix":7},"sk":{"a":0,"k":0,"ix":4},"sa":{"a":0,"k":0,"ix":5},"nm":"Transform"}],"nm":"Ellipse 1","np":3,"cix":2,"ix":1,"mn":"ADBE Vector Group","hd":false}],"ip":13,"op":31,"st":13,"bm":0},{"ddd":0,"ind":3,"ty":4,"nm":"Shape Layer 4","sr":1,"ks":{"o":{"a":0,"k":100,"ix":11},"r":{"a":1,"k":[{"i":{"x":[0.833],"y":[0.833]},"o":{"x":[0.167],"y":[0.167]},"n":["0p833_0p833_0p167_0p167"],"t":15,"s":[0],"e":[-104]},{"i":{"x":[0.833],"y":[0.833]},"o":{"x":[0.167],"y":[0.167]},"n":["0p833_0p833_0p167_0p167"],"t":26,"s":[-104],"e":[-24]},{"t":29}],"ix":10},"p":{"a":1,"k":[{"i":{"x":0.833,"y":0.833},"o":{"x":0.167,"y":0.167},"n":"0p833_0p833_0p167_0p167","t":15,"s":[105.5,434.75,0],"e":[121.25,417.5,0],"to":[1.875,-12.625,0],"ti":[-6.60057020187378,-3.3359637260437,0]},{"i":{"x":0.833,"y":0.833},"o":{"x":0.167,"y":0.167},"n":"0p833_0p833_0p167_0p167","t":21,"s":[121.25,417.5,0],"e":[136.5,466.5,0],"to":[15.4166669845581,7.79166650772095,0],"ti":[-2.75,-9.50486278533936,0]},{"i":{"x":0.833,"y":0.833},"o":{"x":0.167,"y":0.167},"n":"0p833_0p833_0p167_0p167","t":26,"s":[136.5,466.5,0],"e":[137.75,474.529,0],"to":[2.75,9.50486278533936,0],"ti":[-0.20833332836628,-1.33819580078125,0]},{"t":29}],"ix":2},"a":{"a":0,"k":[-237.805,73.171,0],"ix":1},"s":{"a":1,"k":[{"i":{"x":[0.667,0.667,0.667],"y":[1,1,1]},"o":{"x":[0.333,0.333,0.333],"y":[0,0,0]},"n":["0p667_1_0p333_0","0p667_1_0p333_0","0p667_1_0p333_0"],"t":15,"s":[47,47,100],"e":[19,19,100]},{"i":{"x":[0.667,0.667,0.667],"y":[1,1,1]},"o":{"x":[0.333,0.333,0.333],"y":[0,0,0]},"n":["0p667_1_0p333_0","0p667_1_0p333_0","0p667_1_0p333_0"],"t":20,"s":[19,19,100],"e":[52,52,100]},{"i":{"x":[0.667,0.667,0.667],"y":[1,1,1]},"o":{"x":[0.333,0.333,0.333],"y":[0,0,0]},"n":["0p667_1_0p333_0","0p667_1_0p333_0","0p667_1_0p333_0"],"t":21,"s":[52,52,100],"e":[0,0,100]},{"t":29}],"ix":6}},"ao":0,"shapes":[{"ty":"gr","it":[{"ind":0,"ty":"sh","ix":1,"ks":{"a":0,"k":{"i":[[0,0],[0,0],[0,0]],"o":[[0,0],[0,0],[0,0]],"v":[[-236,64.75],[-247.5,76.75],[-227,79.75]],"c":true},"ix":2},"nm":"Path 1","mn":"ADBE Vector Shape - Group","hd":false},{"ty":"st","c":{"a":0,"k":[1,0,0.070588175456,1],"ix":3},"o":{"a":0,"k":100,"ix":4},"w":{"a":0,"k":2,"ix":5},"lc":1,"lj":1,"ml":4,"nm":"Stroke 1","mn":"ADBE Vector Graphic - Stroke","hd":false},{"ty":"tr","p":{"a":0,"k":[0,0],"ix":2},"a":{"a":0,"k":[0,0],"ix":1},"s":{"a":0,"k":[100,100],"ix":3},"r":{"a":0,"k":0,"ix":6},"o":{"a":0,"k":100,"ix":7},"sk":{"a":0,"k":0,"ix":4},"sa":{"a":0,"k":0,"ix":5},"nm":"Transform"}],"nm":"Shape 1","np":3,"cix":2,"ix":1,"mn":"ADBE Vector Group","hd":false}],"ip":13,"op":31,"st":13,"bm":0},{"ddd":0,"ind":4,"ty":4,"nm":"Shape Layer 3","sr":1,"ks":{"o":{"a":0,"k":100,"ix":11},"r":{"a":1,"k":[{"i":{"x":[0.833],"y":[0.833]},"o":{"x":[0.167],"y":[0.167]},"n":["0p833_0p833_0p167_0p167"],"t":15,"s":[-40],"e":[-144]},{"i":{"x":[0.833],"y":[0.833]},"o":{"x":[0.167],"y":[0.167]},"n":["0p833_0p833_0p167_0p167"],"t":26,"s":[-144],"e":[-64]},{"t":29}],"ix":10},"p":{"a":1,"k":[{"i":{"x":0.833,"y":0.833},"o":{"x":0.167,"y":0.167},"n":"0p833_0p833_0p167_0p167","t":15,"s":[74,451.25,0],"e":[51.5,435.5,0],"to":[-5.75,-18.625,0],"ti":[6.41666650772095,-2.91747784614563,0]},{"i":{"x":0.833,"y":0.833},"o":{"x":0.167,"y":0.167},"n":"0p833_0p833_0p167_0p167","t":21,"s":[51.5,435.5,0],"e":[35.5,468.755,0],"to":[-6.41666650772095,2.91747784614563,0],"ti":[-4.58333349227905,-24.0424785614014,0]},{"i":{"x":0.833,"y":0.833},"o":{"x":0.167,"y":0.167},"n":"0p833_0p833_0p167_0p167","t":26,"s":[35.5,468.755,0],"e":[18.75,455.755,0],"to":[1.15178096294403,6.04181861877441,0],"ti":[0.20833332836628,0.00458272313699,0]},{"t":29}],"ix":2},"a":{"a":0,"k":[-274,95,0],"ix":1},"s":{"a":1,"k":[{"i":{"x":[0.667,0.667,0.667],"y":[1,1,1]},"o":{"x":[0.333,0.333,0.333],"y":[0,0,0]},"n":["0p667_1_0p333_0","0p667_1_0p333_0","0p667_1_0p333_0"],"t":15,"s":[65,65,100],"e":[37,37,100]},{"i":{"x":[0.667,0.667,0.667],"y":[1,1,1]},"o":{"x":[0.333,0.333,0.333],"y":[0,0,0]},"n":["0p667_1_0p333_0","0p667_1_0p333_0","0p667_1_0p333_0"],"t":20,"s":[37,37,100],"e":[70,70,100]},{"i":{"x":[0.667,0.667,0.667],"y":[1,1,1]},"o":{"x":[0.333,0.333,0.333],"y":[0,0,0]},"n":["0p667_1_0p333_0","0p667_1_0p333_0","0p667_1_0p333_0"],"t":21,"s":[70,70,100],"e":[0,0,100]},{"t":29}],"ix":6}},"ao":0,"shapes":[{"ty":"gr","it":[{"ind":0,"ty":"sh","ix":1,"ks":{"a":0,"k":{"i":[[0,0],[0,0],[0,0]],"o":[[0,0],[0,0],[0,0]],"v":[[-278.5,86.25],[-283.75,103.5],[-263.5,98]],"c":true},"ix":2},"nm":"Path 1","mn":"ADBE Vector Shape - Group","hd":false},{"ty":"st","c":{"a":0,"k":[0.870588175456,1,0,1],"ix":3},"o":{"a":0,"k":100,"ix":4},"w":{"a":0,"k":2,"ix":5},"lc":1,"lj":1,"ml":4,"nm":"Stroke 1","mn":"ADBE Vector Graphic - Stroke","hd":false},{"ty":"tr","p":{"a":0,"k":[0,0],"ix":2},"a":{"a":0,"k":[0,0],"ix":1},"s":{"a":0,"k":[100,100],"ix":3},"r":{"a":0,"k":0,"ix":6},"o":{"a":0,"k":100,"ix":7},"sk":{"a":0,"k":0,"ix":4},"sa":{"a":0,"k":0,"ix":5},"nm":"Transform"}],"nm":"Shape 1","np":3,"cix":2,"ix":1,"mn":"ADBE Vector Group","hd":false}],"ip":13,"op":31,"st":13,"bm":0}]},{"id":"comp_4","layers":[{"ddd":0,"ind":1,"ty":4,"nm":"Layer 2 Outlines","sr":1,"ks":{"o":{"a":0,"k":100,"ix":11},"r":{"a":0,"k":0,"ix":10},"p":{"a":0,"k":[42,23,0],"ix":2},"a":{"a":0,"k":[2.25,2.25,0],"ix":1},"s":{"a":0,"k":[100,100,100],"ix":6}},"ao":0,"shapes":[{"ty":"gr","it":[{"ind":0,"ty":"sh","ix":1,"ks":{"a":0,"k":{"i":[[0,-1.104],[1.104,0],[0,1.104],[-1.104,0]],"o":[[0,1.104],[-1.104,0],[0,-1.104],[1.104,0]],"v":[[2,0],[0,2],[-2,0],[0,-2]],"c":true},"ix":2},"nm":"Path 1","mn":"ADBE Vector Shape - Group","hd":false},{"ty":"fl","c":{"a":0,"k":[1,1,1,1],"ix":4},"o":{"a":0,"k":100,"ix":5},"r":1,"nm":"Fill 1","mn":"ADBE Vector Graphic - Fill","hd":false},{"ty":"tr","p":{"a":0,"k":[2.25,2.25],"ix":2},"a":{"a":0,"k":[0,0],"ix":1},"s":{"a":0,"k":[100,100],"ix":3},"r":{"a":0,"k":0,"ix":6},"o":{"a":0,"k":100,"ix":7},"sk":{"a":0,"k":0,"ix":4},"sa":{"a":0,"k":0,"ix":5},"nm":"Transform"}],"nm":"Group 1","np":2,"cix":2,"ix":1,"mn":"ADBE Vector Group","hd":false}],"ip":0,"op":713,"st":0,"bm":0},{"ddd":0,"ind":2,"ty":4,"nm":"Layer 3 Outlines","sr":1,"ks":{"o":{"a":0,"k":100,"ix":11},"r":{"a":0,"k":0,"ix":10},"p":{"a":0,"k":[32,37,0],"ix":2},"a":{"a":0,"k":[23.25,23.25,0],"ix":1},"s":{"a":0,"k":[100,100,100],"ix":6}},"ao":0,"shapes":[{"ty":"gr","it":[{"ind":0,"ty":"sh","ix":1,"ks":{"a":0,"k":{"i":[[0,-12.703],[12.703,0],[0,12.702],[-12.703,0]],"o":[[0,12.702],[-12.703,0],[0,-12.703],[12.703,0]],"v":[[23,0],[0,23],[-23,0],[0,-23]],"c":true},"ix":2},"nm":"Path 1","mn":"ADBE Vector Shape - Group","hd":false},{"ty":"fl","c":{"a":0,"k":[0.097999999102,0.081999999402,0.317999985639,1],"ix":4},"o":{"a":0,"k":100,"ix":5},"r":1,"nm":"Fill 1","mn":"ADBE Vector Graphic - Fill","hd":false},{"ty":"tr","p":{"a":0,"k":[23.25,23.25],"ix":2},"a":{"a":0,"k":[0,0],"ix":1},"s":{"a":0,"k":[100,100],"ix":3},"r":{"a":0,"k":0,"ix":6},"o":{"a":0,"k":100,"ix":7},"sk":{"a":0,"k":0,"ix":4},"sa":{"a":0,"k":0,"ix":5},"nm":"Transform"}],"nm":"Group 1","np":2,"cix":2,"ix":1,"mn":"ADBE Vector Group","hd":false}],"ip":0,"op":713,"st":0,"bm":0},{"ddd":0,"ind":3,"ty":4,"nm":"Layer 4 Outlines","sr":1,"ks":{"o":{"a":0,"k":100,"ix":11},"r":{"a":0,"k":0,"ix":10},"p":{"a":0,"k":[33,37,0],"ix":2},"a":{"a":0,"k":[23.25,23.25,0],"ix":1},"s":{"a":0,"k":[100,100,100],"ix":6}},"ao":0,"shapes":[{"ty":"gr","it":[{"ind":0,"ty":"sh","ix":1,"ks":{"a":0,"k":{"i":[[0,-12.703],[12.703,0],[0,12.702],[-12.703,0]],"o":[[0,12.702],[-12.703,0],[0,-12.703],[12.703,0]],"v":[[23,0],[0,23],[-23,0],[0,-23]],"c":true},"ix":2},"nm":"Path 1","mn":"ADBE Vector Shape - Group","hd":false},{"ty":"fl","c":{"a":0,"k":[0.447000002394,0.532999973671,0.728999956916,1],"ix":4},"o":{"a":0,"k":100,"ix":5},"r":1,"nm":"Fill 1","mn":"ADBE Vector Graphic - Fill","hd":false},{"ty":"tr","p":{"a":0,"k":[23.25,23.25],"ix":2},"a":{"a":0,"k":[0,0],"ix":1},"s":{"a":0,"k":[100,100],"ix":3},"r":{"a":0,"k":0,"ix":6},"o":{"a":0,"k":100,"ix":7},"sk":{"a":0,"k":0,"ix":4},"sa":{"a":0,"k":0,"ix":5},"nm":"Transform"}],"nm":"Group 1","np":2,"cix":2,"ix":1,"mn":"ADBE Vector Group","hd":false}],"ip":0,"op":713,"st":0,"bm":0}]},{"id":"comp_5","layers":[{"ddd":0,"ind":1,"ty":4,"nm":"Layer 3 Outlines","sr":1,"ks":{"o":{"a":0,"k":100,"ix":11},"r":{"a":0,"k":0,"ix":10},"p":{"a":0,"k":[223.999,221.051,0],"ix":2},"a":{"a":0,"k":[12.553,13.257,0],"ix":1},"s":{"a":0,"k":[100,100,100],"ix":6}},"ao":0,"shapes":[{"ty":"gr","it":[{"ind":0,"ty":"sh","ix":1,"ks":{"a":0,"k":{"i":[[-7.498,26.014],[13.967,2.655]],"o":[[0,0],[0,0]],"v":[[12.303,-13.007],[-12.303,4.651]],"c":true},"ix":2},"nm":"Path 1","mn":"ADBE Vector Shape - Group","hd":false},{"ty":"fl","c":{"a":0,"k":[1,1,1,1],"ix":4},"o":{"a":0,"k":100,"ix":5},"r":1,"nm":"Fill 1","mn":"ADBE Vector Graphic - Fill","hd":false},{"ty":"tr","p":{"a":0,"k":[12.553,13.257],"ix":2},"a":{"a":0,"k":[0,0],"ix":1},"s":{"a":0,"k":[100,100],"ix":3},"r":{"a":0,"k":0,"ix":6},"o":{"a":0,"k":100,"ix":7},"sk":{"a":0,"k":0,"ix":4},"sa":{"a":0,"k":0,"ix":5},"nm":"Transform"}],"nm":"Group 1","np":2,"cix":2,"ix":1,"mn":"ADBE Vector Group","hd":false}],"ip":0,"op":713,"st":0,"bm":0},{"ddd":0,"ind":2,"ty":4,"nm":"Layer 4 Outlines","sr":1,"ks":{"o":{"a":0,"k":100,"ix":11},"r":{"a":0,"k":0,"ix":10},"p":{"a":0,"k":[126.356,217.25,0],"ix":2},"a":{"a":0,"k":[113.106,23.5,0],"ix":1},"s":{"a":0,"k":[100,100,100],"ix":6}},"ao":0,"shapes":[{"ty":"gr","it":[{"ind":0,"ty":"sh","ix":1,"ks":{"a":0,"k":{"i":[[15.5,39.5],[-53.5,-0.297],[0,0],[-11.287,18.304],[39,-1],[0,0]],"o":[[0,0],[53.5,0.298],[0,0],[0,0],[-39,1],[0,0]],"v":[[-110.357,-23.25],[-59.357,22.952],[83.088,22.75],[112.857,1.555],[54.144,17.25],[-64.857,17.25]],"c":true},"ix":2},"nm":"Path 1","mn":"ADBE Vector Shape - Group","hd":false},{"ty":"fl","c":{"a":0,"k":[0.097999999102,0.081999999402,0.317999985639,1],"ix":4},"o":{"a":0,"k":100,"ix":5},"r":1,"nm":"Fill 1","mn":"ADBE Vector Graphic - Fill","hd":false},{"ty":"tr","p":{"a":0,"k":[113.106,23.5],"ix":2},"a":{"a":0,"k":[0,0],"ix":1},"s":{"a":0,"k":[100,100],"ix":3},"r":{"a":0,"k":0,"ix":6},"o":{"a":0,"k":100,"ix":7},"sk":{"a":0,"k":0,"ix":4},"sa":{"a":0,"k":0,"ix":5},"nm":"Transform"}],"nm":"Group 1","np":2,"cix":2,"ix":1,"mn":"ADBE Vector Group","hd":false}],"ip":0,"op":713,"st":0,"bm":0},{"ddd":0,"ind":3,"ty":4,"nm":"Layer 5 Outlines","sr":1,"ks":{"o":{"a":0,"k":100,"ix":11},"r":{"a":0,"k":0,"ix":10},"p":{"a":0,"k":[218.906,125.725,0],"ix":2},"a":{"a":0,"k":[28.156,120.475,0],"ix":1},"s":{"a":0,"k":[100,100,100],"ix":6}},"ao":0,"shapes":[{"ty":"gr","it":[{"ind":0,"ty":"sh","ix":1,"ks":{"a":0,"k":{"i":[[54.5,-16.5],[-2,-40],[0,0],[30.005,-9.543],[-11.688,47.224],[0,0]],"o":[[0,0],[0,0],[0,0],[0,0],[0,0],[0,0]],"v":[[-27.906,-103.725],[18.094,-71.725],[18.094,73.658],[-15.401,114.232],[27.906,73.001],[27.594,-74.225]],"c":true},"ix":2},"nm":"Path 1","mn":"ADBE Vector Shape - Group","hd":false},{"ty":"fl","c":{"a":0,"k":[0.097999999102,0.081999999402,0.317999985639,1],"ix":4},"o":{"a":0,"k":100,"ix":5},"r":1,"nm":"Fill 1","mn":"ADBE Vector Graphic - Fill","hd":false},{"ty":"tr","p":{"a":0,"k":[28.156,120.475],"ix":2},"a":{"a":0,"k":[0,0],"ix":1},"s":{"a":0,"k":[100,100],"ix":3},"r":{"a":0,"k":0,"ix":6},"o":{"a":0,"k":100,"ix":7},"sk":{"a":0,"k":0,"ix":4},"sa":{"a":0,"k":0,"ix":5},"nm":"Transform"}],"nm":"Group 1","np":2,"cix":2,"ix":1,"mn":"ADBE Vector Group","hd":false}],"ip":0,"op":713,"st":0,"bm":0},{"ddd":0,"ind":4,"ty":4,"nm":"Layer 6 Outlines","sr":1,"ks":{"o":{"a":0,"k":100,"ix":11},"r":{"a":0,"k":0,"ix":10},"p":{"a":0,"k":[131.001,224.374,0],"ix":2},"a":{"a":0,"k":[116.363,30.843,0],"ix":1},"s":{"a":0,"k":[100,100,100],"ix":6}},"ao":0,"shapes":[{"ty":"gr","it":[{"ind":0,"ty":"sh","ix":1,"ks":{"a":0,"k":{"i":[[-0.125,-0.73],[-1.315,-4.23],[-3.606,-5.599],[-14.542,-1.012],[-0.027,0],[0,0],[-0.061,0.012],[-9.644,17.712],[-1.113,2.951],[-1.014,5.947],[0.662,-0.385],[116.855,60.838]],"o":[[0.343,1.992],[1.55,4.986],[6.009,9.33],[0.027,0.002],[0,0],[0.064,0],[1.224,-0.254],[1.302,-2.393],[1.693,-4.488],[0.127,-0.744],[-13.869,8.07],[-0.667,-0.347]],"v":[[-115.988,-28.838],[-113.617,-19.092],[-106.074,-2.538],[-76.131,16.106],[-76.049,16.109],[83.431,16.109],[83.612,16.092],[108.212,-5.086],[111.855,-13.087],[115.986,-28.69],[114.624,-29.599],[-114.66,-29.762]],"c":true},"ix":2},"nm":"Path 1","mn":"ADBE Vector Shape - Group","hd":false},{"ty":"fl","c":{"a":0,"k":[0.344999994016,0.344999994016,0.626999978458,1],"ix":4},"o":{"a":0,"k":100,"ix":5},"r":1,"nm":"Fill 1","mn":"ADBE Vector Graphic - Fill","hd":false},{"ty":"tr","p":{"a":0,"k":[116.363,30.359],"ix":2},"a":{"a":0,"k":[0,0],"ix":1},"s":{"a":0,"k":[100,100],"ix":3},"r":{"a":0,"k":0,"ix":6},"o":{"a":0,"k":100,"ix":7},"sk":{"a":0,"k":0,"ix":4},"sa":{"a":0,"k":0,"ix":5},"nm":"Transform"}],"nm":"Group 1","np":4,"cix":2,"ix":1,"mn":"ADBE Vector Group","hd":false}],"ip":0,"op":713,"st":0,"bm":0},{"ddd":0,"ind":5,"ty":4,"nm":"Layer 7 Outlines","sr":1,"ks":{"o":{"a":0,"k":100,"ix":11},"r":{"a":0,"k":0,"ix":10},"p":{"a":0,"k":[215,36.5,0],"ix":2},"a":{"a":0,"k":[25.25,17.75,0],"ix":1},"s":{"a":0,"k":[100,100,100],"ix":6}},"ao":0,"shapes":[{"ty":"gr","it":[{"ind":0,"ty":"sh","ix":1,"ks":{"a":0,"k":{"i":[[50,-3],[-4,-26]],"o":[[0,0],[0,0]],"v":[[-25,-14.5],[21,17.5]],"c":true},"ix":2},"nm":"Path 1","mn":"ADBE Vector Shape - Group","hd":false},{"ty":"fl","c":{"a":0,"k":[1,1,1,1],"ix":4},"o":{"a":0,"k":100,"ix":5},"r":1,"nm":"Fill 1","mn":"ADBE Vector Graphic - Fill","hd":false},{"ty":"tr","p":{"a":0,"k":[25.25,17.75],"ix":2},"a":{"a":0,"k":[0,0],"ix":1},"s":{"a":0,"k":[100,100],"ix":3},"r":{"a":0,"k":0,"ix":6},"o":{"a":0,"k":100,"ix":7},"sk":{"a":0,"k":0,"ix":4},"sa":{"a":0,"k":0,"ix":5},"nm":"Transform"}],"nm":"Group 1","np":2,"cix":2,"ix":1,"mn":"ADBE Vector Group","hd":false}],"ip":0,"op":713,"st":0,"bm":0},{"ddd":0,"ind":6,"ty":4,"nm":"Layer 8 Outlines","sr":1,"ks":{"o":{"a":0,"k":100,"ix":11},"r":{"a":0,"k":0,"ix":10},"p":{"a":0,"k":[133,138.42,0],"ix":2},"a":{"a":0,"k":[113.25,104.83,0],"ix":1},"s":{"a":0,"k":[100,100,100],"ix":6}},"ao":0,"shapes":[{"ty":"gr","it":[{"ind":0,"ty":"sh","ix":1,"ks":{"a":0,"k":{"i":[[12,25.209],[-173.948,32.339],[-0.188,-8.694],[0,0],[40.505,-3.043],[0,0]],"o":[[0,0],[0,0],[0.188,8.694],[0,0],[-40.505,3.043],[0,0]],"v":[[-113,74.789],[107.552,-104.58],[112.812,-87.114],[112.812,60.306],[69.505,101.537],[-75.845,101.379]],"c":true},"ix":2},"nm":"Path 1","mn":"ADBE Vector Shape - Group","hd":false},{"ty":"fl","c":{"a":0,"k":[0.211999990426,0.211999990426,0.517999985639,1],"ix":4},"o":{"a":0,"k":100,"ix":5},"r":1,"nm":"Fill 1","mn":"ADBE Vector Graphic - Fill","hd":false},{"ty":"tr","p":{"a":0,"k":[113.25,104.83],"ix":2},"a":{"a":0,"k":[0,0],"ix":1},"s":{"a":0,"k":[100,100],"ix":3},"r":{"a":0,"k":0,"ix":6},"o":{"a":0,"k":100,"ix":7},"sk":{"a":0,"k":0,"ix":4},"sa":{"a":0,"k":0,"ix":5},"nm":"Transform"}],"nm":"Group 1","np":2,"cix":2,"ix":1,"mn":"ADBE Vector Group","hd":false}],"ip":0,"op":713,"st":0,"bm":0},{"ddd":0,"ind":7,"ty":4,"nm":"Layer 9 Outlines","sr":1,"ks":{"o":{"a":0,"k":100,"ix":11},"r":{"a":0,"k":0,"ix":10},"p":{"a":0,"k":[131,125,0],"ix":2},"a":{"a":0,"k":[115.25,115.25,0],"ix":1},"s":{"a":0,"k":[100,100,100],"ix":6}},"ao":0,"shapes":[{"ty":"gr","it":[{"ind":0,"ty":"sh","ix":1,"ks":{"a":0,"k":{"i":[[25.087,0],[0,0],[0,25.087],[0,0],[-25.087,0],[0,0],[0,-25.087],[0,0]],"o":[[0,0],[-25.087,0],[0,0],[0,-25.087],[0,0],[25.087,0],[0,0],[0,25.087]],"v":[[69.576,115],[-69.576,115],[-115,69.576],[-115,-69.576],[-69.576,-115],[69.576,-115],[115,-69.576],[115,69.576]],"c":true},"ix":2},"nm":"Path 1","mn":"ADBE Vector Shape - Group","hd":false},{"ty":"fl","c":{"a":0,"k":[0.097999999102,0.081999999402,0.317999985639,1],"ix":4},"o":{"a":0,"k":100,"ix":5},"r":1,"nm":"Fill 1","mn":"ADBE Vector Graphic - Fill","hd":false},{"ty":"tr","p":{"a":0,"k":[115.25,115.25],"ix":2},"a":{"a":0,"k":[0,0],"ix":1},"s":{"a":0,"k":[100,100],"ix":3},"r":{"a":0,"k":0,"ix":6},"o":{"a":0,"k":100,"ix":7},"sk":{"a":0,"k":0,"ix":4},"sa":{"a":0,"k":0,"ix":5},"nm":"Transform"}],"nm":"Group 1","np":2,"cix":2,"ix":1,"mn":"ADBE Vector Group","hd":false}],"ip":0,"op":713,"st":0,"bm":0}]},{"id":"comp_6","layers":[{"ddd":0,"ind":1,"ty":4,"nm":"Layer 2 Outlines","sr":1,"ks":{"o":{"a":0,"k":100,"ix":11},"r":{"a":0,"k":0,"ix":10},"p":{"a":0,"k":[126,119,0],"ix":2},"a":{"a":0,"k":[112.25,104.25,0],"ix":1},"s":{"a":0,"k":[100,100,100],"ix":6}},"ao":0,"shapes":[{"ty":"gr","it":[{"ind":0,"ty":"sh","ix":1,"ks":{"a":0,"k":{"i":[[25.087,0],[0,0],[0,25.087],[0,0],[-25.087,0],[0,0],[0,-25.087],[0,0]],"o":[[0,0],[-25.087,0],[0,0],[0,-25.087],[0,0],[25.087,0],[0,0],[0,25.087]],"v":[[66.576,104],[-66.576,104],[-112,58.576],[-112,-58.576],[-66.576,-104],[66.576,-104],[112,-58.576],[112,58.576]],"c":true},"ix":2},"nm":"Path 1","mn":"ADBE Vector Shape - Group","hd":false},{"ty":"fl","c":{"a":0,"k":[1,1,1,1],"ix":4},"o":{"a":0,"k":100,"ix":5},"r":1,"nm":"Fill 1","mn":"ADBE Vector Graphic - Fill","hd":false},{"ty":"tr","p":{"a":0,"k":[112.25,104.25],"ix":2},"a":{"a":0,"k":[0,0],"ix":1},"s":{"a":0,"k":[100,100],"ix":3},"r":{"a":0,"k":0,"ix":6},"o":{"a":0,"k":100,"ix":7},"sk":{"a":0,"k":0,"ix":4},"sa":{"a":0,"k":0,"ix":5},"nm":"Transform"}],"nm":"Group 1","np":2,"cix":2,"ix":1,"mn":"ADBE Vector Group","hd":false}],"ip":0,"op":713,"st":0,"bm":0},{"ddd":0,"ind":2,"ty":4,"nm":"Layer 3 Outlines","sr":1,"ks":{"o":{"a":0,"k":100,"ix":11},"r":{"a":0,"k":0,"ix":10},"p":{"a":0,"k":[126,130,0],"ix":2},"a":{"a":0,"k":[112.25,104.25,0],"ix":1},"s":{"a":0,"k":[100,100,100],"ix":6}},"ao":0,"shapes":[{"ty":"gr","it":[{"ind":0,"ty":"sh","ix":1,"ks":{"a":0,"k":{"i":[[25.087,0],[0,0],[0,25.087],[0,0],[-25.087,0],[0,0],[0,-25.087],[0,0]],"o":[[0,0],[-25.087,0],[0,0],[0,-25.087],[0,0],[25.087,0],[0,0],[0,25.087]],"v":[[66.576,104],[-66.576,104],[-112,58.576],[-112,-58.576],[-66.576,-104],[66.576,-104],[112,-58.576],[112,58.576]],"c":true},"ix":2},"nm":"Path 1","mn":"ADBE Vector Shape - Group","hd":false},{"ty":"fl","c":{"a":0,"k":[0.745000023935,0.834999952129,0.987999949736,1],"ix":4},"o":{"a":0,"k":100,"ix":5},"r":1,"nm":"Fill 1","mn":"ADBE Vector Graphic - Fill","hd":false},{"ty":"tr","p":{"a":0,"k":[112.25,104.25],"ix":2},"a":{"a":0,"k":[0,0],"ix":1},"s":{"a":0,"k":[100,100],"ix":3},"r":{"a":0,"k":0,"ix":6},"o":{"a":0,"k":100,"ix":7},"sk":{"a":0,"k":0,"ix":4},"sa":{"a":0,"k":0,"ix":5},"nm":"Transform"}],"nm":"Group 1","np":2,"cix":2,"ix":1,"mn":"ADBE Vector Group","hd":false}],"ip":0,"op":713,"st":0,"bm":0},{"ddd":0,"ind":3,"ty":4,"nm":"Layer 4 Outlines","sr":1,"ks":{"o":{"a":0,"k":100,"ix":11},"r":{"a":0,"k":0,"ix":10},"p":{"a":0,"k":[126,130,0],"ix":2},"a":{"a":0,"k":[115.25,115.25,0],"ix":1},"s":{"a":0,"k":[100,100,100],"ix":6}},"ao":0,"shapes":[{"ty":"gr","it":[{"ind":0,"ty":"sh","ix":1,"ks":{"a":0,"k":{"i":[[25.087,0],[0,0],[0,25.087],[0,0],[-25.087,0],[0,0],[0,-25.087],[0,0]],"o":[[0,0],[-25.087,0],[0,0],[0,-25.087],[0,0],[25.087,0],[0,0],[0,25.087]],"v":[[69.576,115],[-69.576,115],[-115,69.576],[-115,-69.576],[-69.576,-115],[69.576,-115],[115,-69.576],[115,69.576]],"c":true},"ix":2},"nm":"Path 1","mn":"ADBE Vector Shape - Group","hd":false},{"ty":"fl","c":{"a":0,"k":[0.925,0.675,0.987999949736,1],"ix":4},"o":{"a":0,"k":100,"ix":5},"r":1,"nm":"Fill 1","mn":"ADBE Vector Graphic - Fill","hd":false},{"ty":"tr","p":{"a":0,"k":[115.25,115.25],"ix":2},"a":{"a":0,"k":[0,0],"ix":1},"s":{"a":0,"k":[100,100],"ix":3},"r":{"a":0,"k":0,"ix":6},"o":{"a":0,"k":100,"ix":7},"sk":{"a":0,"k":0,"ix":4},"sa":{"a":0,"k":0,"ix":5},"nm":"Transform"}],"nm":"Group 1","np":2,"cix":2,"ix":1,"mn":"ADBE Vector Group","hd":false}],"ip":0,"op":713,"st":0,"bm":0}]}],"layers":[{"ddd":0,"ind":1,"ty":0,"nm":"Pre-comp 7","refId":"comp_0","sr":1,"ks":{"o":{"a":0,"k":100,"ix":11},"r":{"a":0,"k":0,"ix":10},"p":{"a":0,"k":[500,500,0],"ix":2},"a":{"a":0,"k":[500,500,0],"ix":1},"s":{"a":0,"k":[100,100,100],"ix":6}},"ao":0,"w":1000,"h":1000,"ip":0,"op":713,"st":0,"bm":0}],"markers":[]}